{
  "version": "1.0",
  "metadata": {
    "id": 1237,
    "slug": "priglashenie-na-den-rozhdenija-v-zolotom-stile-s-shampanskim-i-ciframi",
    "title": "Приглашение на день рождения в золотом стиле с шампанским и цифрами",
    "categoryIds": [
      19,
      20,
      18,
      21
    ],
    "categorySlugs": [
      "woman",
      "man",
      "invitations",
      "balloons"
    ],
    "categoryNames": [
      "День рождения женщины",
      "День рождения мужчины",
      "Приглашения",
      "Шары-цифры"
    ],
    "preview": "/templates/priglashenie-na-den-rozhdenija-v-zolotom-stile-s-shampanskim-i-ciframi/preview.webp",
    "sourceUrl": "https://evyt.ru/design/priglashenie-na-den-rozhdenija-v-zolotom-stile-s-shampanskim-i-ciframi/"
  },
  "stage": {
    "width": 481,
    "height": 683
  },
  "canvas": {
    "width": 1748,
    "height": 2482,
    "background": "#ffffff"
  },
  "fonts": [
    {
      "family": "Isabelle",
      "url": "/tpl-assets/fpd_fonts/Isabelle.ttf"
    },
    {
      "family": "Melody",
      "url": "/tpl-assets/fpd_fonts/Melody.ttf"
    },
    {
      "family": "Lora",
      "url": "/tpl-assets/fpd_fonts/Lora.ttf"
    },
    {
      "family": "Thea",
      "url": "/tpl-assets/fpd_fonts/Thea.ttf"
    }
  ],
  "objects": [
    {
      "type": "image",
      "version": "5.3.0",
      "src": "/tpl-assets/2024/10/birthday-1007-8.jpg",
      "left": 874,
      "top": 1241.043659043659,
      "scaleX": 1.0020790020790018,
      "scaleY": 1.0020790020790018,
      "angle": 0,
      "originX": "center",
      "originY": "center",
      "opacity": 1,
      "selectable": false,
      "evented": false,
      "lockMovementX": true,
      "lockMovementY": true,
      "lockRotation": true,
      "lockScalingX": true,
      "lockScalingY": true
    },
    {
      "type": "i-text",
      "version": "5.3.0",
      "text": "ДЕНЬ РОЖДЕНИЯ",
      "left": 874,
      "top": 1621.3986555240454,
      "scaleX": 1,
      "scaleY": 1,
      "angle": 0,
      "originX": "center",
      "originY": "center",
      "opacity": 1,
      "fontFamily": "Isabelle",
      "fontSize": 222,
      "fill": "#f9d138",
      "textAlign": "left",
      "fontWeight": "normal",
      "fontStyle": "normal",
      "underline": false,
      "lineHeight": 1,
      "charSpacing": 0,
      "styles": {},
      "selectable": true,
      "evented": true,
      "editable": true
    },
    {
      "type": "i-text",
      "version": "5.3.0",
      "text": "Приглашаю на",
      "left": 874,
      "top": 1387.188346169757,
      "scaleX": 1,
      "scaleY": 1,
      "angle": 0,
      "originX": "center",
      "originY": "center",
      "opacity": 1,
      "fontFamily": "Melody",
      "fontSize": 174,
      "fill": "#ffffff",
      "textAlign": "left",
      "fontWeight": "normal",
      "fontStyle": "normal",
      "underline": false,
      "lineHeight": 1,
      "charSpacing": 0,
      "styles": {},
      "selectable": true,
      "evented": true,
      "editable": true
    },
    {
      "type": "i-text",
      "version": "5.3.0",
      "text": "Собираемся в 20:00",
      "left": 874,
      "top": 1942.0341576886083,
      "scaleX": 1,
      "scaleY": 1,
      "angle": 0,
      "originX": "center",
      "originY": "center",
      "opacity": 1,
      "fontFamily": "Melody",
      "fontSize": 120,
      "fill": "#f9d138",
      "textAlign": "left",
      "fontWeight": "normal",
      "fontStyle": "normal",
      "underline": false,
      "lineHeight": 1,
      "charSpacing": 0,
      "styles": {},
      "selectable": true,
      "evented": true,
      "editable": true
    },
    {
      "type": "i-text",
      "version": "5.3.0",
      "text": "РЕСТОРАН «ПАРАДАЙЗ» \nГ. МОСКВА, УЛ. ПРАЗДНИКА, 7",
      "left": 874,
      "top": 2134.4720253569317,
      "scaleX": 1,
      "scaleY": 1,
      "angle": 0,
      "originX": "center",
      "originY": "center",
      "opacity": 1,
      "fontFamily": "Lora",
      "fontSize": 58,
      "fill": "#ffffff",
      "textAlign": "center",
      "fontWeight": "normal",
      "fontStyle": "normal",
      "underline": false,
      "lineHeight": 1,
      "charSpacing": 0,
      "styles": {},
      "selectable": true,
      "evented": true,
      "editable": true
    },
    {
      "type": "i-text",
      "version": "5.3.0",
      "text": "20 НОЯБРЯ",
      "left": 874,
      "top": 1803.1804953251678,
      "scaleX": 1,
      "scaleY": 1,
      "angle": 0,
      "originX": "center",
      "originY": "center",
      "opacity": 1,
      "fontFamily": "Thea",
      "fontSize": 91,
      "fill": "#ffffff",
      "textAlign": "left",
      "fontWeight": "normal",
      "fontStyle": "normal",
      "underline": false,
      "lineHeight": 1,
      "charSpacing": 0,
      "styles": {},
      "selectable": true,
      "evented": true,
      "editable": true
    },
    {
      "type": "i-text",
      "version": "5.3.0",
      "text": "Ваш, Евгений",
      "left": 874,
      "top": 2316.3535127176597,
      "scaleX": 1,
      "scaleY": 1,
      "angle": 0,
      "originX": "center",
      "originY": "center",
      "opacity": 1,
      "fontFamily": "Melody",
      "fontSize": 109,
      "fill": "#f9d138",
      "textAlign": "left",
      "fontWeight": "normal",
      "fontStyle": "normal",
      "underline": false,
      "lineHeight": 1,
      "charSpacing": 0,
      "styles": {},
      "selectable": true,
      "evented": true,
      "editable": true
    },
    {
      "type": "image",
      "version": "5.3.0",
      "src": "/tpl-assets/2024/10/number-5-gold.png",
      "left": 1045.647164324411,
      "top": 871.8956298341365,
      "scaleX": 0.8377044698544699,
      "scaleY": 0.8377044698544699,
      "angle": 0,
      "originX": "center",
      "originY": "center",
      "opacity": 1,
      "selectable": false,
      "evented": false,
      "lockMovementX": true,
      "lockMovementY": true,
      "lockRotation": true,
      "lockScalingX": true,
      "lockScalingY": true
    },
    {
      "type": "image",
      "version": "5.3.0",
      "src": "/tpl-assets/2024/10/number-4-gold.png",
      "left": 638.7976918549801,
      "top": 875.5265329976896,
      "scaleX": 0.9006870230810811,
      "scaleY": 0.9006870230810811,
      "angle": 0,
      "originX": "center",
      "originY": "center",
      "opacity": 1,
      "selectable": false,
      "evented": false,
      "lockMovementX": true,
      "lockMovementY": true,
      "lockRotation": true,
      "lockScalingX": true,
      "lockScalingY": true
    }
  ]
}