{
  "version": "1.0",
  "metadata": {
    "id": 2790,
    "slug": "priglashenie-na-jubilej-s-rozovymi-vozdushnymi-sharami",
    "title": "Приглашение на юбилей с розовыми воздушными шарами",
    "categoryIds": [
      18,
      27,
      22
    ],
    "categorySlugs": [
      "invitations",
      "anniversary",
      "womans"
    ],
    "categoryNames": [
      "Приглашения",
      "Юбилей",
      "Юбилей женщины"
    ],
    "preview": "/templates/priglashenie-na-jubilej-s-rozovymi-vozdushnymi-sharami/preview.webp",
    "sourceUrl": "https://evyt.ru/design/priglashenie-na-jubilej-s-rozovymi-vozdushnymi-sharami/"
  },
  "stage": {
    "width": 481,
    "height": 683
  },
  "canvas": {
    "width": 1748,
    "height": 2482,
    "background": "#ffffff"
  },
  "fonts": [
    {
      "family": "Flora Bold",
      "url": "/tpl-assets/fpd_fonts/Flora_Bold.ttf"
    },
    {
      "family": "Kendall",
      "url": "/tpl-assets/fpd_fonts/Kendall.ttf"
    },
    {
      "family": "Thea",
      "url": "/tpl-assets/fpd_fonts/Thea.ttf"
    }
  ],
  "objects": [
    {
      "type": "image",
      "version": "5.3.0",
      "src": "/tpl-assets/2024/12/invitation-design-1113-3.webp",
      "left": 874,
      "top": 1241.043659043659,
      "scaleX": 1.006237006237006,
      "scaleY": 1.006237006237006,
      "angle": 0,
      "originX": "center",
      "originY": "center",
      "opacity": 1,
      "selectable": false,
      "evented": false,
      "lockMovementX": true,
      "lockMovementY": true,
      "lockRotation": true,
      "lockScalingX": true,
      "lockScalingY": true
    },
    {
      "type": "i-text",
      "version": "5.3.0",
      "text": "ДЕНЬ РОЖДЕНИЯ",
      "left": 874,
      "top": 1563.3042049071942,
      "scaleX": 1,
      "scaleY": 1,
      "angle": 0,
      "originX": "center",
      "originY": "center",
      "opacity": 1,
      "fontFamily": "Flora Bold",
      "fontSize": 222,
      "fill": "#e05071",
      "textAlign": "left",
      "fontWeight": "normal",
      "fontStyle": "normal",
      "underline": false,
      "lineHeight": 1,
      "charSpacing": 0,
      "styles": {},
      "selectable": true,
      "evented": true,
      "editable": true
    },
    {
      "type": "i-text",
      "version": "5.3.0",
      "text": "Приглашаю на",
      "left": 874,
      "top": 1365.4029271884376,
      "scaleX": 1,
      "scaleY": 1,
      "angle": 0,
      "originX": "center",
      "originY": "center",
      "opacity": 1,
      "fontFamily": "Kendall",
      "fontSize": 98,
      "fill": "#e05071",
      "textAlign": "left",
      "fontWeight": "normal",
      "fontStyle": "normal",
      "underline": false,
      "lineHeight": 1,
      "charSpacing": 0,
      "styles": {},
      "selectable": true,
      "evented": true,
      "editable": true
    },
    {
      "type": "i-text",
      "version": "5.3.0",
      "text": "Собираемся в 20:00",
      "left": 874,
      "top": 1909.3560292166296,
      "scaleX": 1,
      "scaleY": 1,
      "angle": 0,
      "originX": "center",
      "originY": "center",
      "opacity": 1,
      "fontFamily": "Kendall",
      "fontSize": 73,
      "fill": "#e05071",
      "textAlign": "left",
      "fontWeight": "normal",
      "fontStyle": "normal",
      "underline": false,
      "lineHeight": 1,
      "charSpacing": 0,
      "styles": {},
      "selectable": true,
      "evented": true,
      "editable": true
    },
    {
      "type": "i-text",
      "version": "5.3.0",
      "text": "РЕСТОРАН «ПАРАДАЙЗ» \nГ. МОСКВА, УЛ. ПРАЗДНИКА, 7",
      "left": 874,
      "top": 2123.5793158662727,
      "scaleX": 1,
      "scaleY": 1,
      "angle": 0,
      "originX": "center",
      "originY": "center",
      "opacity": 1,
      "fontFamily": "Thea",
      "fontSize": 65,
      "fill": "#e05071",
      "textAlign": "center",
      "fontWeight": "normal",
      "fontStyle": "normal",
      "underline": false,
      "lineHeight": 1,
      "charSpacing": 0,
      "styles": {},
      "selectable": true,
      "evented": true,
      "editable": true
    },
    {
      "type": "i-text",
      "version": "5.3.0",
      "text": "20 НОЯБРЯ",
      "left": 874,
      "top": 1748.7169478718697,
      "scaleX": 1,
      "scaleY": 1,
      "angle": 0,
      "originX": "center",
      "originY": "center",
      "opacity": 1,
      "fontFamily": "Thea",
      "fontSize": 91,
      "fill": "#e05071",
      "textAlign": "left",
      "fontWeight": "normal",
      "fontStyle": "normal",
      "underline": false,
      "lineHeight": 1,
      "charSpacing": 0,
      "styles": {},
      "selectable": true,
      "evented": true,
      "editable": true
    },
    {
      "type": "i-text",
      "version": "5.3.0",
      "text": "Ваша, Ксения",
      "left": 874,
      "top": 2327.2462360591176,
      "scaleX": 1,
      "scaleY": 1,
      "angle": 0,
      "originX": "center",
      "originY": "center",
      "opacity": 1,
      "fontFamily": "Kendall",
      "fontSize": 55,
      "fill": "#e05071",
      "textAlign": "left",
      "fontWeight": "normal",
      "fontStyle": "normal",
      "underline": false,
      "lineHeight": 1,
      "charSpacing": 0,
      "styles": {},
      "selectable": true,
      "evented": true,
      "editable": true
    }
  ]
}