{
  "version": "1.0",
  "metadata": {
    "id": 7940,
    "slug": "priglasitelnoe-na-detskij-master-klass",
    "title": "Пригласительное на детский мастер-класс",
    "categoryIds": [
      61,
      18
    ],
    "categorySlugs": [
      "kids-workshop",
      "invitations"
    ],
    "categoryNames": [
      "Мастер-класс для детей",
      "Приглашения"
    ],
    "preview": "/templates/priglasitelnoe-na-detskij-master-klass/preview.webp",
    "sourceUrl": "https://evyt.ru/design/priglasitelnoe-na-detskij-master-klass/"
  },
  "stage": {
    "width": 481,
    "height": 683
  },
  "canvas": {
    "width": 1748,
    "height": 2482,
    "background": "#ffffff"
  },
  "fonts": [
    {
      "family": "Isabelle",
      "url": "/tpl-assets/fpd_fonts/Isabelle.ttf"
    },
    {
      "family": "Amelia",
      "url": "/tpl-assets/fpd_fonts/Amelia.ttf"
    }
  ],
  "objects": [
    {
      "type": "image",
      "version": "5.3.0",
      "src": "/tpl-assets/2026/01/invitation-design-0401-54.jpg",
      "left": 874,
      "top": 1241.043659043659,
      "scaleX": 1.0041580041580043,
      "scaleY": 1.0041580041580043,
      "angle": 0,
      "originX": "center",
      "originY": "center",
      "opacity": 1,
      "selectable": false,
      "evented": false,
      "lockMovementX": true,
      "lockMovementY": true,
      "lockRotation": true,
      "lockScalingX": true,
      "lockScalingY": true
    },
    {
      "type": "i-text",
      "version": "5.3.0",
      "text": "МАСТЕР-КЛАСС ДЛЯ ДЕТЕЙ",
      "left": 874,
      "top": 1805.1223639103168,
      "scaleX": 1,
      "scaleY": 1,
      "angle": 0,
      "originX": "center",
      "originY": "center",
      "opacity": 1,
      "fontFamily": "Isabelle",
      "fontSize": 193,
      "fill": "#3994bb",
      "textAlign": "center",
      "fontWeight": "normal",
      "fontStyle": "normal",
      "underline": false,
      "lineHeight": 0.9,
      "charSpacing": 0,
      "styles": {},
      "selectable": true,
      "evented": true,
      "editable": true
    },
    {
      "type": "i-text",
      "version": "5.3.0",
      "text": "Начало в 14:00",
      "left": 873.9999999999999,
      "top": 2101.793896884952,
      "scaleX": 1,
      "scaleY": 1,
      "angle": 0,
      "originX": "center",
      "originY": "center",
      "opacity": 1,
      "fontFamily": "Amelia",
      "fontSize": 138,
      "fill": "#ef7a3d",
      "textAlign": "center",
      "fontWeight": "normal",
      "fontStyle": "normal",
      "underline": false,
      "lineHeight": 1,
      "charSpacing": 0,
      "styles": {},
      "selectable": true,
      "evented": true,
      "editable": true
    },
    {
      "type": "i-text",
      "version": "5.3.0",
      "text": "ТВОРЧЕСКАЯ СТУДИЯ «РАДУГА»\nГ. МОСКВА, УЛ. ДЕТСКАЯ, 7",
      "left": 874,
      "top": 2282.6128751224433,
      "scaleX": 1,
      "scaleY": 1,
      "angle": 0,
      "originX": "center",
      "originY": "center",
      "opacity": 1,
      "fontFamily": "Isabelle",
      "fontSize": 84,
      "fill": "#3994bb",
      "textAlign": "center",
      "fontWeight": "normal",
      "fontStyle": "normal",
      "underline": false,
      "lineHeight": 1,
      "charSpacing": 0,
      "styles": {},
      "selectable": true,
      "evented": true,
      "editable": true
    },
    {
      "type": "i-text",
      "version": "5.3.0",
      "text": "10 апреля",
      "left": 874,
      "top": 1970.2020218037724,
      "scaleX": 1,
      "scaleY": 1,
      "angle": 0,
      "originX": "center",
      "originY": "center",
      "opacity": 1,
      "fontFamily": "Isabelle",
      "fontSize": 109,
      "fill": "#79b030",
      "textAlign": "left",
      "fontWeight": "normal",
      "fontStyle": "normal",
      "underline": false,
      "lineHeight": 1,
      "charSpacing": 0,
      "styles": {},
      "selectable": true,
      "evented": true,
      "editable": true
    },
    {
      "type": "i-text",
      "version": "5.3.0",
      "text": "Приглашение на",
      "left": 874,
      "top": 1615.9216350594434,
      "scaleX": 1,
      "scaleY": 1,
      "angle": 0,
      "originX": "center",
      "originY": "center",
      "opacity": 1,
      "fontFamily": "Amelia",
      "fontSize": 153,
      "fill": "#ef7a3d",
      "textAlign": "left",
      "fontWeight": "normal",
      "fontStyle": "normal",
      "underline": false,
      "lineHeight": 1,
      "charSpacing": 0,
      "styles": {},
      "selectable": true,
      "evented": true,
      "editable": true
    }
  ]
}