{
  "version": "1.0",
  "metadata": {
    "id": 2131,
    "slug": "priglashenie-na-den-rozhdenija-s-pljushevym-mishkoj",
    "title": "Приглашение на день рождения с плюшевым мишкой",
    "categoryIds": [
      52,
      18
    ],
    "categorySlugs": [
      "boy",
      "invitations"
    ],
    "categoryNames": [
      "День рождения мальчика",
      "Приглашения"
    ],
    "preview": "/templates/priglashenie-na-den-rozhdenija-s-pljushevym-mishkoj/preview.webp",
    "sourceUrl": "https://evyt.ru/design/priglashenie-na-den-rozhdenija-s-pljushevym-mishkoj/"
  },
  "stage": {
    "width": 481,
    "height": 683
  },
  "canvas": {
    "width": 1748,
    "height": 2482,
    "background": "#ffffff"
  },
  "fonts": [
    {
      "family": "Anna",
      "url": "/tpl-assets/fpd_fonts/Anna.ttf"
    },
    {
      "family": "Alora",
      "url": "/tpl-assets/fpd_fonts/Alora.ttf"
    },
    {
      "family": "Isabelle",
      "url": "/tpl-assets/fpd_fonts/Isabelle.ttf"
    },
    {
      "family": "Flora Bold",
      "url": "/tpl-assets/fpd_fonts/Flora_Bold.ttf"
    }
  ],
  "objects": [
    {
      "type": "image",
      "version": "5.3.0",
      "src": "/tpl-assets/2024/11/invitation-design-6.webp",
      "left": 874,
      "top": 1241.043659043659,
      "scaleX": 1.0041580041580043,
      "scaleY": 1.0041580041580043,
      "angle": 0,
      "originX": "center",
      "originY": "center",
      "opacity": 1,
      "selectable": false,
      "evented": false,
      "lockMovementX": true,
      "lockMovementY": true,
      "lockRotation": true,
      "lockScalingX": true,
      "lockScalingY": true
    },
    {
      "type": "i-text",
      "version": "5.3.0",
      "text": "ДЕНЬ\nРОЖДЕНИЯ",
      "left": 579.6908103019723,
      "top": 970.9044858365713,
      "scaleX": 1,
      "scaleY": 1,
      "angle": 0,
      "originX": "center",
      "originY": "center",
      "opacity": 1,
      "fontFamily": "Anna",
      "fontSize": 298,
      "fill": "#44a2e9",
      "textAlign": "center",
      "fontWeight": "normal",
      "fontStyle": "normal",
      "underline": false,
      "lineHeight": 0.9,
      "charSpacing": 0,
      "styles": {},
      "selectable": true,
      "evented": true,
      "editable": true
    },
    {
      "type": "i-text",
      "version": "5.3.0",
      "text": "Марку исполняется \n1 годик!",
      "left": 554.3325573454472,
      "top": 1458.897848856852,
      "scaleX": 1,
      "scaleY": 1,
      "angle": 0,
      "originX": "center",
      "originY": "center",
      "opacity": 1,
      "fontFamily": "Alora",
      "fontSize": 138,
      "fill": "#111111",
      "textAlign": "center",
      "fontWeight": "normal",
      "fontStyle": "normal",
      "underline": false,
      "lineHeight": 0.9,
      "charSpacing": 0,
      "styles": {},
      "selectable": true,
      "evented": true,
      "editable": true
    },
    {
      "type": "i-text",
      "version": "5.3.0",
      "text": "Приглашение на",
      "left": 542.5571635237151,
      "top": 544.636452357802,
      "scaleX": 1,
      "scaleY": 1,
      "angle": 0,
      "originX": "center",
      "originY": "center",
      "opacity": 1,
      "fontFamily": "Alora",
      "fontSize": 145,
      "fill": "#000000",
      "textAlign": "left",
      "fontWeight": "normal",
      "fontStyle": "normal",
      "underline": false,
      "lineHeight": 1,
      "charSpacing": 0,
      "styles": {},
      "selectable": true,
      "evented": true,
      "editable": true
    },
    {
      "type": "i-text",
      "version": "5.3.0",
      "text": "10 марта в 16:00",
      "left": 554.3325573454472,
      "top": 1723.7287211842324,
      "scaleX": 1,
      "scaleY": 1,
      "angle": 0,
      "originX": "center",
      "originY": "center",
      "opacity": 1,
      "fontFamily": "Isabelle",
      "fontSize": 109,
      "fill": "#dc8464",
      "textAlign": "left",
      "fontWeight": "normal",
      "fontStyle": "normal",
      "underline": false,
      "lineHeight": 1,
      "charSpacing": 0,
      "styles": {},
      "selectable": true,
      "evented": true,
      "editable": true
    },
    {
      "type": "i-text",
      "version": "5.3.0",
      "text": "Собираемся по адресу: \nг. Москва, ул. Праздника, 7",
      "left": 554.3325573454472,
      "top": 1922.7022204335385,
      "scaleX": 1,
      "scaleY": 1,
      "angle": 0,
      "originX": "center",
      "originY": "center",
      "opacity": 1,
      "fontFamily": "Flora Bold",
      "fontSize": 80,
      "fill": "#000000",
      "textAlign": "center",
      "fontWeight": "normal",
      "fontStyle": "normal",
      "underline": false,
      "lineHeight": 0.9,
      "charSpacing": 0,
      "styles": {},
      "selectable": true,
      "evented": true,
      "editable": true
    },
    {
      "type": "i-text",
      "version": "5.3.0",
      "text": "Ждём на празднике!",
      "left": 554.3325573454472,
      "top": 2127.729039026558,
      "scaleX": 1,
      "scaleY": 1,
      "angle": 0,
      "originX": "center",
      "originY": "center",
      "opacity": 1,
      "fontFamily": "Alora",
      "fontSize": 116,
      "fill": "#dc8464",
      "textAlign": "center",
      "fontWeight": "normal",
      "fontStyle": "normal",
      "underline": false,
      "lineHeight": 0.9,
      "charSpacing": 0,
      "styles": {},
      "selectable": true,
      "evented": true,
      "editable": true
    },
    {
      "type": "image",
      "version": "5.3.0",
      "src": "/tpl-assets/2024/10/number-1-blue.webp",
      "left": 1154.5335621560905,
      "top": 544.636452357802,
      "scaleX": 1.1198760494454512,
      "scaleY": 1.1198760494454512,
      "angle": 0,
      "originX": "center",
      "originY": "center",
      "opacity": 1,
      "selectable": false,
      "evented": false,
      "lockMovementX": true,
      "lockMovementY": true,
      "lockRotation": true,
      "lockScalingX": true,
      "lockScalingY": true
    }
  ]
}